tarandm_analytics_utils/__init__.cpython-313-x86_64-linux-gnu.so
tarandm_analytics_utils/__init__.pyi
tarandm_analytics_utils/predictive_models/__init__.cpython-313-x86_64-linux-gnu.so
tarandm_analytics_utils/predictive_models/__init__.pyi
tarandm_analytics_utils/predictive_models/attribute_preprocessing/__init__.cpython-313-x86_64-linux-gnu.so
tarandm_analytics_utils/predictive_models/attribute_preprocessing/__init__.pyi
tarandm_analytics_utils/predictive_models/attribute_preprocessing/attribute_binning.cpython-313-x86_64-linux-gnu.so
tarandm_analytics_utils/predictive_models/attribute_preprocessing/attribute_binning.pyi
tarandm_analytics_utils/predictive_models/attribute_preprocessing/attribute_preprocessing.cpython-313-x86_64-linux-gnu.so
tarandm_analytics_utils/predictive_models/attribute_preprocessing/attribute_preprocessing.pyi
tarandm_analytics_utils/predictive_models/attribute_preprocessing/attribute_transformation.cpython-313-x86_64-linux-gnu.so
tarandm_analytics_utils/predictive_models/attribute_preprocessing/attribute_transformation.pyi
tarandm_analytics_utils/predictive_models/content.cpython-313-x86_64-linux-gnu.so
tarandm_analytics_utils/predictive_models/content.pyi
tarandm_analytics_utils/predictive_models/extended_predictive_model.cpython-313-x86_64-linux-gnu.so
tarandm_analytics_utils/predictive_models/extended_predictive_model.pyi
tarandm_analytics_utils/predictive_models/model_description/__init__.cpython-313-x86_64-linux-gnu.so
tarandm_analytics_utils/predictive_models/model_description/__init__.pyi
tarandm_analytics_utils/predictive_models/model_description/model_description.cpython-313-x86_64-linux-gnu.so
tarandm_analytics_utils/predictive_models/model_description/model_description.pyi
tarandm_analytics_utils/predictive_models/model_description/sample_decription.cpython-313-x86_64-linux-gnu.so
tarandm_analytics_utils/predictive_models/model_description/sample_decription.pyi
tarandm_analytics_utils-1.1.8.dist-info/METADATA
tarandm_analytics_utils-1.1.8.dist-info/WHEEL
tarandm_analytics_utils-1.1.8.dist-info/RECORD
