Metadata-Version: 2.4
Name: tarandm_analytics_utils
Version: 1.1.8
Summary: Package provides support for analytics methods and models in TaranDM.
Author: Matej Scerba
Author-email: mscerba@taran.ai
Requires-Python: >=3.9,<3.14
Classifier: Programming Language :: Python :: 3
Classifier: Programming Language :: Python :: 3.9
Classifier: Programming Language :: Python :: 3.10
Classifier: Programming Language :: Python :: 3.11
Classifier: Programming Language :: Python :: 3.12
Classifier: Programming Language :: Python :: 3.13
Requires-Dist: pep8
Requires-Dist: pydantic
Requires-Dist: requests
Requires-Dist: ruamel-yaml
Requires-Dist: strawberry-graphql
Requires-Dist: structlog
